Metadata-Version: 2.1
Name: odoo14-addon-ebill_postfinance_customer_free_ref
Version: 14.0.1.0.1.dev2
Summary: Glue module: ebill_postfinance and sale_order_customer_free_ref
Home-page: https://github.com/OCA/l10n-switzerland
Author: Camptocamp,Odoo Community Association (OCA)
Author-email: support@odoo-community.org
License: AGPL-3
Classifier: Programming Language :: Python
Classifier: Framework :: Odoo
Classifier: Framework :: Odoo :: 14.0
Classifier: License :: OSI Approved :: GNU Affero General Public License v3
Requires-Python: >=3.6
Requires-Dist: odoo14-addon-ebill-postfinance
Requires-Dist: odoo14-addon-sale-order-customer-free-ref
Requires-Dist: odoo <14.1dev,>=14.0a
